xnor_popcount.vhd
----------------------------------------------------------------------------------
-- Company: FAU & UPC
-- Engineer: Jannis Wolf
-- 
-- Create Date:    13:07:58 11/12/2020 
-- Design Name:    bnn_acc
-- Module Name:    xnor_popcount - Behavioral 
-- Project Name:   FPGA Binary Neural Network Accelerator
-- Target Devices: 
-- Tool versions: 
-- Description: 
--
-- Dependencies: 
--
----------------------------------------------------------------------------------
library IEEE;
use IEEE.STD_LOGIC_1164.ALL;
use IEEE.NUMERIC_STD.ALL;

----------------------------------------------------------------------------------
-- Entity
----------------------------------------------------------------------------------

entity xnor_popcount is
   GENERIC(
	    size : integer := 10
		 );
   PORT(
	    clk_xn : IN STD_LOGIC;
	    wei : IN STD_LOGIC_VECTOR(size-1 downto 0);
		 d_in : IN STD_LOGIC_VECTOR(size-1 downto 0);
		 res : OUT STD_LOGIC
	);
end xnor_popcount;

----------------------------------------------------------------------------------
-- Architecture
----------------------------------------------------------------------------------

architecture Behavioral of xnor_popcount is

----------------------------------------------------------------------------------
-- Signal & Variables
----------------------------------------------------------------------------------

signal cou : std_logic_vector(size-1 downto 0) := (others => '0');
--variable pop_count : unsigned(3 downto 0) := "0000"; 
signal sig_pop : std_logic_vector(7 downto 0) := "00000000";
signal sig_count : std_logic_vector(3 downto 0) := "0000";
signal sig_res : signed(7 downto 0) := "00000000";


----------------------------------------------------------------------------------
-- Components
----------------------------------------------------------------------------------



----------------------------------------------------------------------------------
-- Processes
----------------------------------------------------------------------------------

begin

op_xnor : process(clk_xn)
begin
cou <= wei xnor d_in;

end process op_xnor;


op_popcount: process(clk_xn, wei)
    variable count : signed(3 downto 0) := (others => '0');
	 variable pop : signed(7 downto 0) := (others => '0');
	 
	 constant num_bit : signed(7 downto 0) := to_signed(size,8);
begin
   if(rising_edge(clk_xn)) then
		count := "0000";

		for i in 0 to size-1 loop
			count := count + ("000" & cou(i)); 
		end loop;

		pop := "000" & count(3 downto 0) & '0'; 
		sig_pop <= std_logic_vector(pop);
		sig_count <= std_logic_vector(count);
		sig_res <= pop - num_bit;
		res <= std_logic(not sig_res(7));
	end if;

end process op_popcount;

end Behavioral;

src/fpga_logic/TASTE-VHDL-XISE/tb_xnor.vhd
--------------------------------------------------------------------------------
-- Company: 
-- Engineer:
--
-- Create Date:   14:09:48 11/24/2020
-- Design Name:   
-- Module Name:   /home/jannis/Code/fpga_bnn_accelerator/src/fpga_logic/TASTE-VHDL-XISE/tb_xnor.vhd
-- Project Name:  Example1
-- Target Device:  
-- Tool versions:  
-- Description:   
-- 
-- VHDL Test Bench Created by ISE for module: xnor_popcount
-- 
-- Dependencies:
-- 
-- Revision:
-- Revision 0.01 - File Created
-- Additional Comments:
--
-- Notes: 
-- This testbench has been automatically generated using types std_logic and
-- std_logic_vector for the ports of the unit under test.  Xilinx recommends
-- that these types always be used for the top-level I/O of a design in order
-- to guarantee that the testbench will bind correctly to the post-implementation 
-- simulation model.
--------------------------------------------------------------------------------
LIBRARY ieee;
USE ieee.std_logic_1164.ALL;
 
-- Uncomment the following library declaration if using
-- arithmetic functions with Signed or Unsigned values
--USE ieee.numeric_std.ALL;
 
ENTITY tb_xnor IS
END tb_xnor;
 
ARCHITECTURE behavior OF tb_xnor IS 
 
    -- Component Declaration for the Unit Under Test (UUT)
 
    COMPONENT xnor_popcount
    PORT(
         clk_xn : IN  std_logic;
         wei : IN  std_logic_vector(9 downto 0);
         d_in : IN  std_logic_vector(9 downto 0);
         res : OUT  std_logic
        );
    END COMPONENT;
    

   --Inputs
   signal clk_xn : std_logic := '0';
   signal wei : std_logic_vector(9 downto 0) := (others => '0');
   signal d_in : std_logic_vector(9 downto 0) := (others => '0');

 	--Outputs
   signal res : std_logic;

   -- Clock period definitions
   constant clk_xn_period : time := 10 ns;
 
BEGIN
 
	-- Instantiate the Unit Under Test (UUT)
   uut: xnor_popcount PORT MAP (
          clk_xn => clk_xn,
          wei => wei,
          d_in => d_in,
          res => res
        );

   -- Clock process definitions
   clk_xn_process :process
   begin
		clk_xn <= '0';
		wait for clk_xn_period/2;
		clk_xn <= '1';
		wait for clk_xn_period/2;
   end process;
 

   -- Stimulus process
   stim_proc: process
   begin		
      -- hold reset state for 100 ns.
		wei <= "1111111111";
      wait for 10 ns;	

      wait for clk_xn_period*10;

      -- insert stimulus here 

		wait for 10 ns;	
      wei <= "0000000000";
		wait for 10 ns;	
		wei <= "1000000000";
		wait for 10 ns;	
		wei <= "1100000000";
		wait for 10 ns;	
		wei <= "1110000000";
		wait for 10 ns;	
		wei <= "1111000000";
		wait for 10 ns;	
		wei <= "1111100000";
		wait for 10 ns;	
		wei <= "1111110000";
		wait for 10 ns;	
		wei <= "1111111000";
		wait for 10 ns;	
		wei <= "1111111100";
		wait for 10 ns;	
		wei <= "1111111110";
		wait for 10 ns;	
		wei <= "1111111111";
      wait;
		
   end process;

END;

xnor.vcd
$date
  Thu Jun 10 22:05:12 2021
$end
$version
  GHDL v0
$end
$timescale
  1 fs
$end
$scope module standard $end
$upscope $end
$scope module std_logic_1164 $end
$upscope $end
$scope module numeric_std $end
$upscope $end
$scope module tb_xnor $end
$var reg 1 ! clk_xn $end
$var reg 10 " wei[9:0] $end
$var reg 10 # d_in[9:0] $end
$var reg 1 $ res $end
$scope module uut $end
$var reg 1 % clk_xn $end
$var reg 10 & wei[9:0] $end
$var reg 10 ' d_in[9:0] $end
$var reg 1 ( res $end
$var reg 10 ) cou[9:0] $end
$var reg 8 * sig_pop[7:0] $end
$var reg 4 + sig_count[3:0] $end
$var reg 8 , sig_res[7:0] $end
$upscope $end
$upscope $end
$enddefinitions $end
#0
0!
b1111111111 "
b0000000000 #
U$
0%
b1111111111 &
b0000000000 '
U(
b1111111111 )
b00000000 *
b0000 +
b00000000 ,
#5000000
1!
1$
1%
1(
b0000000000 )
b00010100 *
b1010 +
b00001010 ,
#10000000
0!
0%
#15000000
1!
1%
b00000000 *
b0000 +
b11110110 ,
#20000000
0!
0%
#25000000
1!
0$
1%
0(
#30000000
0!
0%
#35000000
1!
1%
#40000000
0!
0%
#45000000
1!
1%
#50000000
0!
0%
#55000000
1!
1%
#60000000
0!
0%
#65000000
1!
1%
#70000000
0!
0%
#75000000
1!
1%
#80000000
0!
0%
#85000000
1!
1%
#90000000
0!
0%
#95000000
1!
1%
#100000000
0!
0%
#105000000
1!
1%
#110000000
0!
0%
#115000000
1!
1%
#120000000
0!
b0000000000 "
0%
b0000000000 &
b1111111111 )
#125000000
1!
1%
b00010100 *
b1010 +
b00001010 ,
#130000000
0!
b1000000000 "
0%
b1000000000 &
b0111111111 )
#135000000
1!
1$
1%
1(
b00010010 *
b1001 +
b00001000 ,
#140000000
0!
b1100000000 "
0%
b1100000000 &
b0011111111 )
#145000000
1!
1%
b00010000 *
b1000 +
b00000110 ,
#150000000
0!
b1110000000 "
0%
b1110000000 &
b0001111111 )
#155000000
1!
1%
b00001110 *
b0111 +
b00000100 ,
#160000000
0!
b1111000000 "
0%
b1111000000 &
b0000111111 )
#165000000
1!
1%
b00001100 *
b0110 +
b00000010 ,
#170000000
0!
b1111100000 "
0%
b1111100000 &
b0000011111 )
#175000000
1!
1%
b00001010 *
b0101 +
b00000000 ,
#180000000
0!
b1111110000 "
0%
b1111110000 &
b0000001111 )
#185000000
1!
1%
b00001000 *
b0100 +
b11111110 ,
#190000000
0!
b1111111000 "
0%
b1111111000 &
b0000000111 )
#195000000
1!
0$
1%
0(
b00000110 *
b0011 +
b11111100 ,
#200000000
0!
b1111111100 "
0%
b1111111100 &
b0000000011 )
#205000000
1!
1%
b00000100 *
b0010 +
b11111010 ,
#210000000
0!
b1111111110 "
0%
b1111111110 &
b0000000001 )
#215000000
1!
1%
b00000010 *
b0001 +
b11111000 ,
#220000000
0!
b1111111111 "
0%
b1111111111 &
b0000000000 )
#225000000
1!
1%
b00000000 *
b0000 +
b11110110 ,
